drf_elasticsearch_dsl/__init__.py
drf_elasticsearch_dsl/apps.py
drf_elasticsearch_dsl/connection_handler.py
drf_elasticsearch_dsl/documents.py
drf_elasticsearch_dsl/helpers.py
drf_elasticsearch_dsl/models.py
drf_elasticsearch_dsl/tasks.py
drf_elasticsearch_dsl/urls.py
drf_elasticsearch_dsl/utils.py
drf_elasticsearch_dsl/views.py
drf_elasticsearch_dsl/management/__init__.py
drf_elasticsearch_dsl/management/commands/__init__.py
drf_elasticsearch_dsl/management/commands/update_index.py
drf_elasticsearch_dsl/signals/__init__.py
drf_elasticsearch_dsl/signals/celery_signal_processor.py
drf_elasticsearch_dsl/static/css/dj_package.css
drf_elasticsearch_dsl/static/js/dj_package.js
drf_elasticsearch_dsl/templates/dj_package/base.html
drf_elasticsearch_dsl-0.1.4.dist-info/DESCRIPTION.rst
drf_elasticsearch_dsl-0.1.4.dist-info/METADATA
drf_elasticsearch_dsl-0.1.4.dist-info/RECORD
drf_elasticsearch_dsl-0.1.4.dist-info/WHEEL
drf_elasticsearch_dsl-0.1.4.dist-info/metadata.json
drf_elasticsearch_dsl-0.1.4.dist-info/top_level.txt
