Metadata-Version: 2.0
Name: drf-elasticsearch-dsl
Version: 0.1.4
Summary: DRF wrapper around ElasticsearchDSL
Home-page: https://github.com/ajbeach2/drf-elasticsearch-dsl
Author: Alexander Beach
Author-email: ajbeach2@gmail.com
License: MIT
Keywords: drf-elasticsearch-dsl
Platform: UNKNOWN
Classifier: Development Status :: 3 - Alpha
Classifier: Framework :: Django
Classifier: Framework :: Django :: 2.0
Classifier: Environment :: Web Environment
Classifier: Intended Audience :: Developers
Classifier: License :: OSI Approved :: MIT License
Classifier: Natural Language :: English
Classifier: Programming Language :: Python :: 3
Classifier: Programming Language :: Python :: 3.3
Classifier: Programming Language :: Python :: 3.4
Classifier: Programming Language :: Python :: 3.5
Classifier: Programming Language :: Python :: 3.6
Requires-Dist: Django
Requires-Dist: djangorestframework
Requires-Dist: elasticsearch-dsl
Provides-Extra: celery
Requires-Dist: celery; extra == 'celery'
